dnstemple/__init__.py
dnstemple-1.0.1.dist-info/LICENSE.md
dnstemple-1.0.1.dist-info/METADATA
dnstemple-1.0.1.dist-info/WHEEL
dnstemple-1.0.1.dist-info/entry_points.txt
dnstemple-1.0.1.dist-info/top_level.txt
dnstemple-1.0.1.dist-info/zip-safe
dnstemple-1.0.1.dist-info/RECORD
