Metadata-Version: 2.1
Name: dnstemple
Version: 1.0.1
Summary: Simple DNS TEMPLating Engine
Home-page: https://netfuture.ch/tools/dnstemple/
Author: Marcel Waldvogel
Author-email: marcel.waldvogel@trifence.ch
License: MIT
Project-URL: GitLab, https://gitlab.com/MarcelWaldvogel/dnstemple/
Project-URL: GitHub, https://github.com/MarcelWaldvogel/dnstemple/
Classifier: Development Status :: 5 - Production/Stable
Classifier: Environment :: Console
Classifier: Intended Audience :: Information Technology
Classifier: Programming Language :: Python :: 3
Classifier: License :: OSI Approved :: MIT License
Classifier: Operating System :: OS Independent
Classifier: Natural Language :: English
Classifier: Topic :: Utilities
Requires-Python: >=3.5
License-File: LICENSE.md
Requires-Dist: setuptools
Requires-Dist: importlib-metadata
Requires-Dist: dnspython
Requires-Dist: PyYAML
